space_invaders/__init__.py
space_invaders/assets/alien.gif
space_invaders/assets/blockade.png
space_invaders/assets/Laser.png
space_invaders/assets/player.png
space_invaders/components/__init__.py
space_invaders/components/base_objects.py
space_invaders/components/blockade.py
space_invaders/components/controller.py
space_invaders/components/game_handler.py
space_invaders/components/laser.py
space_invaders/components/level.py
space_invaders/components/objects.py
space_invaders/components/player.py
space_invaders/components/scoreboard.py
space_invaders/config.yaml
space_invaders/gym_env/__init__.py
space_invaders/gym_env/space_invader_env.py
space_invaders/main.py
space_invaders_niklas_mueller-1.0.2.dist-info/LICENSE
space_invaders_niklas_mueller-1.0.2.dist-info/METADATA
space_invaders_niklas_mueller-1.0.2.dist-info/WHEEL
space_invaders_niklas_mueller-1.0.2.dist-info/RECORD
