Metadata-Version: 2.1
Name: space-invaders-niklas-mueller
Version: 1.0.2
Summary: A custom space invaders game using Pygame for human and computer players.
Author: Niklas Mueller
Author-email: n.mueller@medienagentur24.eu
Requires-Python: >=3.12,<4.0
Classifier: Programming Language :: Python :: 3
Classifier: Programming Language :: Python :: 3.12
Requires-Dist: gymnasium (>=0.29.1,<0.30.0)
Requires-Dist: numpy (>=1.26.3,<2.0.0)
Requires-Dist: pillow (>=10.2.0,<11.0.0)
Requires-Dist: pygame (>=2.5.2,<3.0.0)
Requires-Dist: pyyaml (>=6.0.1,<7.0.0)
